dependencyhealth/__init__.py
dependencyhealth/abstract_client.py
dependencyhealth/exceptions.py
dependencyhealth/npm/__init__.py
dependencyhealth/npm/client.py
dependencyhealth-0.1.0.dist-info/LICENSE
dependencyhealth-0.1.0.dist-info/METADATA
dependencyhealth-0.1.0.dist-info/WHEEL
dependencyhealth-0.1.0.dist-info/RECORD
